LICENSE.txt
README.md
pyproject.toml
src/jijsolver/__init__.py
src/jijsolver/channel.py
src/jijsolver/config.py
src/jijsolver/solve.py
src/jijsolver_api_client.egg-info/PKG-INFO
src/jijsolver_api_client.egg-info/SOURCES.txt
src/jijsolver_api_client.egg-info/dependency_links.txt
src/jijsolver_api_client.egg-info/requires.txt
src/jijsolver_api_client.egg-info/top_level.txt
src/jijsolver_proto/jijsolver_pb2.py
src/jijsolver_proto/jijsolver_pb2.pyi
src/jijsolver_proto/jijsolver_pb2_grpc.py
tests/test_config.py