Metadata-Version: 2.4
Name: jijsolver_api_client
Version: 0.1.0
Summary: A client for JijSolver API.
Author-email: "Jij Inc." <info@j-ij.com>
License: JijSolver API Client Terms of Use
Requires-Python: >=3.9
License-File: LICENSE.txt
Requires-Dist: ommx<2.0.0,>=1.8.0
Requires-Dist: grpcio<2.0.0,>=1.69.0
Provides-Extra: dev
Requires-Dist: pytest; extra == "dev"
Requires-Dist: requests; extra == "dev"
Dynamic: license-file
